django_filemaker_pyodbc/__init__.py
django_filemaker_pyodbc/base.py
django_filemaker_pyodbc/client.py
django_filemaker_pyodbc/compat.py
django_filemaker_pyodbc/compiler.py
django_filemaker_pyodbc/creation.py
django_filemaker_pyodbc/features.py
django_filemaker_pyodbc/operations.py
django_filemaker_pyodbc-0.0.13.dist-info/LICENSE
django_filemaker_pyodbc-0.0.13.dist-info/METADATA
django_filemaker_pyodbc-0.0.13.dist-info/WHEEL
django_filemaker_pyodbc-0.0.13.dist-info/top_level.txt
django_filemaker_pyodbc-0.0.13.dist-info/RECORD
