Metadata-Version: 2.1
Name: django-filemaker-pyodbc
Version: 0.0.13
Summary: Django Database Engine for Filemaker using pyodbc
Home-page: https://bitbucket.org/csmu/django-filemaker-pyodbc
Author: Keith John Hutchison - Ceiteach Seán Mac Úistin
Author-email: keith@bd2l.com.au
License: UNKNOWN
Platform: UNKNOWN
Classifier: Programming Language :: Python :: 3
Classifier: License :: OSI Approved :: Apache Software License
Classifier: Operating System :: OS Independent
Requires-Python: >=3.6
